django_x402/__init__.py
django_x402/facilitators.py
django_x402/middleware.py
django_x402/urls.py
django_x402/views.py
django_x402-0.0.1.dist-info/METADATA
django_x402-0.0.1.dist-info/WHEEL
django_x402-0.0.1.dist-info/licenses/LICENSE
django_x402-0.0.1.dist-info/RECORD
