Metadata-Version: 2.4
Name: django-x402
Version: 0.0.1
Summary: Django middleware for the x402 'Payment Required' protocol
Author: Conner Swann
License: MIT
License-File: LICENSE
Keywords: 402,django,middleware,payments,x402
Classifier: Development Status :: 4 - Beta
Classifier: Framework :: Django
Classifier: Framework :: Django :: 5.2
Classifier: Intended Audience :: Developers
Classifier: License :: OSI Approved :: MIT License
Classifier: Operating System :: OS Independent
Classifier: Programming Language :: Python :: 3
Classifier: Programming Language :: Python :: 3 :: Only
Classifier: Programming Language :: Python :: 3.10
Classifier: Programming Language :: Python :: 3.11
Classifier: Programming Language :: Python :: 3.12
Classifier: Programming Language :: Python :: 3.13
Classifier: Topic :: Software Development :: Libraries :: Python Modules
Requires-Python: >=3.10
Requires-Dist: django>=5.2
Requires-Dist: eth-account>=0.13.4
Requires-Dist: httpx>=0.27.0
Requires-Dist: web3>=6.20.0
Requires-Dist: x402>=0.1.0
Provides-Extra: tests
Requires-Dist: anyio>=4.0.0; extra == 'tests'
Requires-Dist: hexbytes>=0.3.1; extra == 'tests'
Requires-Dist: pytest-django>=4.8.0; extra == 'tests'
Requires-Dist: pytest>=8; extra == 'tests'
Requires-Dist: respx>=0.21.1; extra == 'tests'
